cognify_sdk/__init__.py
cognify_sdk/client.py
cognify_sdk/config.py
cognify_sdk/exceptions.py
cognify_sdk/http_client.py
cognify_sdk/types.py
cognify_sdk/utils.py
cognify_sdk/auth/__init__.py
cognify_sdk/auth/auth_module.py
cognify_sdk/auth/base.py
cognify_sdk/auth/middleware.py
cognify_sdk/auth/token_manager.py
cognify_sdk/collections/__init__.py
cognify_sdk/collections/analytics.py
cognify_sdk/collections/collaboration.py
cognify_sdk/collections/collections_module.py
cognify_sdk/collections/models.py
cognify_sdk/conversations/__init__.py
cognify_sdk/conversations/analytics.py
cognify_sdk/conversations/context_manager.py
cognify_sdk/conversations/conversations_module.py
cognify_sdk/conversations/models.py
cognify_sdk/documents/__init__.py
cognify_sdk/documents/documents_module.py
cognify_sdk/documents/models.py
cognify_sdk/documents/upload.py
cognify_sdk/query/__init__.py
cognify_sdk/query/batch.py
cognify_sdk/query/history.py
cognify_sdk/query/models.py
cognify_sdk/query/query_module.py
cognify_sdk/query/suggestions.py
cognify_sdk/rag/__init__.py
cognify_sdk/rag/agents.py
cognify_sdk/rag/models.py
cognify_sdk/rag/rag_module.py
cognify_sdk/rag/streaming.py
cognify_sdk-0.1.0.dist-info/METADATA
cognify_sdk-0.1.0.dist-info/WHEEL
cognify_sdk-0.1.0.dist-info/licenses/LICENSE
cognify_sdk-0.1.0.dist-info/RECORD
